hns/__init__.py
hns/cli.py
hns-1.0.6.dist-info/METADATA
hns-1.0.6.dist-info/WHEEL
hns-1.0.6.dist-info/entry_points.txt
hns-1.0.6.dist-info/licenses/LICENSE
hns-1.0.6.dist-info/RECORD
