Metadata-Version: 2.4
Name: hns
Version: 1.0.6
Summary: A simple, privacy-focused speech-to-text CLI tool
Project-URL: Homepage, https://github.com/primaprashant/hns
Project-URL: Issues, https://github.com/primaprashant/hns/issues
License-Expression: MIT
License-File: LICENSE
Classifier: Operating System :: OS Independent
Classifier: Programming Language :: Python :: 3
Requires-Python: >=3.10
Requires-Dist: click>=8.2.1
Requires-Dist: faster-whisper>=1.1.1
Requires-Dist: numpy>=2.2.6
Requires-Dist: pyperclip>=1.9.0
Requires-Dist: rich>=13.0.0
Requires-Dist: sounddevice>=0.5.2
